README.rst
setup.py
releaselog/__init__.py
releaselog/config.py
releaselog/releaselog.py
releaselog.egg-info/PKG-INFO
releaselog.egg-info/SOURCES.txt
releaselog.egg-info/dependency_links.txt
releaselog.egg-info/entry_points.txt
releaselog.egg-info/top_level.txt