Metadata-Version: 1.1
Name: releaselog
Version: 0.1
Summary: Generate release notess from git commit logs.
Home-page: https://www.bitbucket.org/Rorosha/releaselog/
Author: Mike Ruckman
Author-email: roshi@fedorapeople.org
License: UNKNOWN
Platform: UNKNOWN
Classifier: Development Status :: 3 - Alpha
Classifier: Intended Audience :: Developers
Classifier: Topic :: Software Development :: Documentation
Classifier: License :: OSI Approved :: GNU General Public License v2 or later (GPLv2+)
Classifier: Programming Language :: Python :: 2.7
